sdw_api/__init__.py
sdw_api/api_class.py
sdw_api-0.1.3.dist-info/WHEEL
sdw_api-0.1.3.dist-info/METADATA
sdw_api-0.1.3.dist-info/RECORD
