Metadata-Version: 2.1
Name: sdw-api
Version: 0.1.3
Summary: Allows downloading data from the ECB's Statistical Data Warehouse (SDW)
Home-page: https://github.com/MaximilianSchroeder/SDW_API
License: MIT
Author: Max
Author-email: maximilian.schroder@bi.no
Requires-Python: >=3.9,<4.0
Classifier: License :: OSI Approved :: MIT License
Classifier: Programming Language :: Python :: 3
Classifier: Programming Language :: Python :: 3.10
Classifier: Programming Language :: Python :: 3.9
Requires-Dist: beautifulsoup4 (>=4.10.0,<5.0.0)
Requires-Dist: pandas (>=1.3.4,<2.0.0)
Requires-Dist: requests (>=2.26.0,<3.0.0)
Project-URL: Repository, https://github.com/MaximilianSchroeder/SDW_API
